cryptlib/__init__.py
cryptlib/random_generator.py
cryptlib/thread_crypt.py
lib/random_generator.py
lib/thread_crypt.py
AdvancedCryptLib-1.3.dist-info/METADATA
AdvancedCryptLib-1.3.dist-info/WHEEL
AdvancedCryptLib-1.3.dist-info/top_level.txt
AdvancedCryptLib-1.3.dist-info/RECORD
