Metadata-Version: 2.1
Name: AdvancedCryptLib
Version: 1.3
Summary: library with cryptography algorithms.
Home-page: https://pypi.org/project/AdvancedCryptLib
Author: the kEnGuRu
License: GPL2
Platform: UNKNOWN
